__macrotype__/macrotype/__init__.pyi
__macrotype__/macrotype/__main__.pyi
__macrotype__/macrotype/emit.pyi
__macrotype__/macrotype/meta_types.pyi
__macrotype__/macrotype/normalize.pyi
__macrotype__/macrotype/resolve.pyi
__macrotype__/macrotype/scanner.pyi
__macrotype__/macrotype/stubgen.pyi
__macrotype__/macrotype/symbols.pyi
__macrotype__/macrotype/typecheck.pyi
__macrotype__/macrotype/watch.pyi
__macrotype__/macrotype/__init__/__init__.pyi
__macrotype__/macrotype/cli/__init__.pyi
__macrotype__/macrotype/cli/typecheck.pyi
__macrotype__/macrotype/cli/watch.pyi
__macrotype__/macrotype/cli/__init__/__init__.pyi
__macrotype__/macrotype/modules/__init__.pyi
__macrotype__/macrotype/modules/emit.pyi
__macrotype__/macrotype/modules/ir.pyi
__macrotype__/macrotype/modules/scanner.pyi
__macrotype__/macrotype/modules/source.pyi
__macrotype__/macrotype/modules/symbols.pyi
__macrotype__/macrotype/modules/transformers/__init__.pyi
__macrotype__/macrotype/modules/transformers/add_comment.pyi
__macrotype__/macrotype/modules/transformers/alias.pyi
__macrotype__/macrotype/modules/transformers/constant.pyi
__macrotype__/macrotype/modules/transformers/dataclass.pyi
__macrotype__/macrotype/modules/transformers/decorator.pyi
__macrotype__/macrotype/modules/transformers/descriptor.pyi
__macrotype__/macrotype/modules/transformers/duplicate.pyi
__macrotype__/macrotype/modules/transformers/enum.pyi
__macrotype__/macrotype/modules/transformers/flag.pyi
__macrotype__/macrotype/modules/transformers/foreign_symbol.pyi
__macrotype__/macrotype/modules/transformers/generic.pyi
__macrotype__/macrotype/modules/transformers/namedtuple.pyi
__macrotype__/macrotype/modules/transformers/newtype.pyi
__macrotype__/macrotype/modules/transformers/overload.pyi
__macrotype__/macrotype/modules/transformers/param_default.pyi
__macrotype__/macrotype/modules/transformers/protocol.pyi
__macrotype__/macrotype/modules/transformers/recover_custom_generics.pyi
macrotype-0.3.0.dist-info/licenses/LICENSE
macrotype-0.3.0.dist-info/METADATA
macrotype-0.3.0.dist-info/WHEEL
macrotype-0.3.0.dist-info/entry_points.txt
macrotype-0.3.0.dist-info/top_level.txt
macrotype-0.3.0.dist-info/RECORD
