Metadata-Version: 2.4
Name: macrotype
Version: 0.3.0
Summary: Generate .pyi stub files from existing modules
Author-email: Kurt Rose <kurt@kurtrose.com>
License: MIT License
Classifier: Programming Language :: Python :: 3
Classifier: Programming Language :: Python :: 3 :: Only
Classifier: License :: OSI Approved :: MIT License
Classifier: Operating System :: OS Independent
Requires-Python: >=3.12
License-File: LICENSE
Provides-Extra: test
Requires-Dist: mypy; extra == "test"
Requires-Dist: pyright; extra == "test"
Requires-Dist: ruff; extra == "test"
Requires-Dist: pytest; extra == "test"
Requires-Dist: sqlalchemy; extra == "test"
Provides-Extra: build
Requires-Dist: build; extra == "build"
Requires-Dist: twine; extra == "build"
Dynamic: license-file
